.coveragerc
.gitignore
.gitlab-ci.yml
CHANGELOG.rst
CONTRIBUTING.rst
LICENSE
MANIFEST.in
Makefile
README.rst
pyproject.toml
setup.cfg
setup.py
doc/Makefile
doc/changelog.rst
doc/conf.py
doc/contribute.rst
doc/examples.rst
doc/index.rst
doc/make.bat
doc/_static/default.css
doc/_static/default_gallery_thumbnail.png
doc/gen_modules/.gitkeep
examples/README.rst
examples/plot_basics.py
src/hesspix/__init__.py
src/hesspix/ct5.py
src/hesspix/version.py
src/hesspix.egg-info/PKG-INFO
src/hesspix.egg-info/SOURCES.txt
src/hesspix.egg-info/dependency_links.txt
src/hesspix.egg-info/requires.txt
src/hesspix.egg-info/top_level.txt
tests/test_is_mandatory.py