Metadata-Version: 2.1
Name: hesspix
Version: 0.2.1
Summary: A tiny library to read HESS pixel info from ROOT files.
Home-page: https://git.ecap.work/tgal/hesspix
Author: Tamas Gal
Author-email: tamas.gal@fau.de
Maintainer: Tamas Gal
Maintainer-email: tamas.gal@fau.de
License: MIT
Keywords: astroparticle,physics,HEP
Classifier: Development Status :: 5 - Production/Stable
Classifier: Intended Audience :: Developers
Classifier: Intended Audience :: Science/Research
Classifier: License :: OSI Approved :: BSD License
Classifier: Operating System :: OS Independent
Classifier: Programming Language :: Python
Classifier: Programming Language :: Python :: 3
Classifier: Programming Language :: Python :: 3 :: Only
Classifier: Programming Language :: Python :: 3.7
Classifier: Programming Language :: Python :: 3.8
Classifier: Programming Language :: Python :: 3.9
Classifier: Programming Language :: Python :: 3.10
Classifier: Topic :: Scientific/Engineering
Requires-Python: >=3.6
License-File: LICENSE
Requires-Dist: setuptools_scm
Requires-Dist: numpy
Requires-Dist: uproot
Provides-Extra: all
Requires-Dist: black; extra == "all"
Requires-Dist: matplotlib; extra == "all"
Requires-Dist: numpydoc; extra == "all"
Requires-Dist: ipykernel; extra == "all"
Requires-Dist: pillow; extra == "all"
Requires-Dist: pytest; extra == "all"
Requires-Dist: pytest-cov; extra == "all"
Requires-Dist: pytest-flake8; extra == "all"
Requires-Dist: pylint; extra == "all"
Requires-Dist: pytest-watch; extra == "all"
Requires-Dist: sphinx; extra == "all"
Requires-Dist: sphinx-autoapi; extra == "all"
Requires-Dist: sphinx-gallery>=0.12.1; extra == "all"
Requires-Dist: sphinx_rtd_theme; extra == "all"
Requires-Dist: sphinxcontrib-versioning; extra == "all"
Requires-Dist: wheel; extra == "all"
Provides-Extra: dev
Requires-Dist: black; extra == "dev"
Requires-Dist: matplotlib; extra == "dev"
Requires-Dist: numpydoc; extra == "dev"
Requires-Dist: ipykernel; extra == "dev"
Requires-Dist: pillow; extra == "dev"
Requires-Dist: pytest; extra == "dev"
Requires-Dist: pytest-cov; extra == "dev"
Requires-Dist: pytest-flake8; extra == "dev"
Requires-Dist: pylint; extra == "dev"
Requires-Dist: pytest-watch; extra == "dev"
Requires-Dist: sphinx; extra == "dev"
Requires-Dist: sphinx-autoapi; extra == "dev"
Requires-Dist: sphinx-gallery>=0.1.12; extra == "dev"
Requires-Dist: sphinx_rtd_theme; extra == "dev"
Requires-Dist: sphinxcontrib-versioning; extra == "dev"
Requires-Dist: wheel; extra == "dev"
